asyncinotify/__init__.py
asyncinotify/_ffi.py
asyncinotify/py.typed
asyncinotify-4.2.2.dist-info/licenses/LICENSE
asyncinotify-4.2.2.dist-info/WHEEL
asyncinotify-4.2.2.dist-info/METADATA
asyncinotify-4.2.2.dist-info/RECORD
