Metadata-Version: 2.4
Name: asyncinotify
Version: 4.2.2
Summary: 'A simple optionally-async python inotify library, focused on simplicity of use and operation, and leveraging modern Python features
Keywords: async,inotify
Author-email: "Taylor C. Richberger" <taylor.richberger@procern.com>
Requires-Python: >= 3.6, < 4
License-Expression: MPL-2.0
Classifier: Development Status :: 6 - Mature
Classifier: Programming Language :: Python :: 3
Classifier: Programming Language :: Python :: 3.6
Classifier: Operating System :: POSIX :: Linux
Classifier: Topic :: Software Development :: Libraries
Classifier: Topic :: Software Development :: Libraries :: Python Modules
Classifier: Intended Audience :: Developers
Classifier: Framework :: AsyncIO
License-File: LICENSE
Project-URL: documentation, https://asyncinotify.readthedocs.io/
Project-URL: repository, https://github.com/ProCern/asyncinotify/
